poetry_analysis-0.3.14.dist-info/METADATA
poetry_analysis-0.3.14.dist-info/WHEEL
poetry_analysis-0.3.14.dist-info/entry_points.txt
poetry_analysis-0.3.14.dist-info/licenses/LICENSE
poetry_analysis/__init__.py
poetry_analysis/alliteration.py
poetry_analysis/anaphora.py
poetry_analysis/lyrical_subject.py
poetry_analysis/rhyme_detection.py
poetry_analysis/utils.py
poetry_analysis-0.3.14.dist-info/RECORD
