Metadata-Version: 2.1
Name: poetry-analysis
Version: 0.3.14
Summary: Tool to parse and annotate Norwegian poetry.
Author-Email: Ingerid Dale <ingerid.dale@nb.no>, Ranveig Kvinnsland <ranveig.kvinnsland@ibsen.uio.no>
License: CC-BY-4.0
Project-URL: Repository, https://github.com/norn-uio/poetry-analysis.git
Project-URL: Issues, https://github.com/norn-uio/poetry-analysis/issues
Project-URL: Documentation, https://norn-uio.github.io/poetry-analysis/
Requires-Python: >=3.11
Requires-Dist: nb-tokenizer
Requires-Dist: pandas
Requires-Dist: convert-pa
Requires-Dist: matplotlib
Provides-Extra: docs
Requires-Dist: mkdocs>=1.6.1; extra == "docs"
Requires-Dist: mkdocs-material>=9.6.21; extra == "docs"
Requires-Dist: mkdocstrings>=0.30.1; extra == "docs"
Requires-Dist: mkdocstrings-python>=1.18.2; extra == "docs"
Requires-Dist: pymdown-extensions>=10.16.1; extra == "docs"
Requires-Dist: nbconvert>=7.16.6; extra == "docs"
Requires-Dist: mkdocs-jupyter>=0.25.1; extra == "docs"
Requires-Dist: jupytext; extra == "docs"
